ligo/em_bright/__init__.py
ligo/em_bright/categorize.py
ligo/em_bright/computeDiskMass.py
ligo/em_bright/dag_writer.py
ligo/em_bright/data/__init__.py
ligo/em_bright/em_bright.py
ligo/em_bright/tests/__init__.py
ligo/em_bright/tests/data/test_categorize_data.tbl
ligo/em_bright/tests/data/test_categorize_ssm_data.csv
ligo/em_bright/tests/test_em_bright.py
ligo/em_bright/utils.py
ligo_em_bright-1.2.2.dist-info/LICENSE
ligo_em_bright-1.2.2.dist-info/METADATA
ligo_em_bright-1.2.2.dist-info/WHEEL
ligo_em_bright-1.2.2.dist-info/entry_points.txt
ligo_em_bright-1.2.2.dist-info/RECORD
