Metadata-Version: 2.1
Name: ligo.em-bright
Version: 1.2.2
Summary: Possibility and properties of Electromagnetically-bright sources of gravitational-wave events
License: MIT
Author: Deep Chatterjee
Author-email: deep.chatterjee@ligo.org
Requires-Python: >=3.10
Classifier: License :: OSI Approved :: MIT License
Classifier: Programming Language :: Python :: 3
Classifier: Programming Language :: Python :: 3.10
Classifier: Programming Language :: Python :: 3.11
Classifier: Programming Language :: Python :: 3.12
Requires-Dist: astropy (>=6.0,<7.0)
Requires-Dist: h5py (>=3.11,<4.0)
Requires-Dist: lalsuite (>=7.23,<8.0)
Requires-Dist: numpy
Requires-Dist: pandas (>=2.2,<3.0)
Requires-Dist: scikit-learn (==1.5.1)
